WebSecProbe/__init__.py
WebSecProbe/main.py
WebSecProbe-0.0.12.dist-info/LICENSE
WebSecProbe-0.0.12.dist-info/METADATA
WebSecProbe-0.0.12.dist-info/WHEEL
WebSecProbe-0.0.12.dist-info/entry_points.txt
WebSecProbe-0.0.12.dist-info/top_level.txt
WebSecProbe-0.0.12.dist-info/RECORD
