Metadata-Version: 2.1
Name: WebSecProbe
Version: 0.0.12
Summary: Bypass 403
Home-page: https://github.com/spyboy-productions/WebSecProbe/
Author: Spyboy
Author-email: contact@spyboy.in
License: MIT
Keywords: HTTP-Request-Analysis,bypass-403,Header-Injection,Historical-Analysis,Payload-Variations,Vulnerability-Assessment
Classifier: Development Status :: 1 - Planning
Classifier: Intended Audience :: Developers
Classifier: Programming Language :: Python :: 3
Classifier: Operating System :: Unix
Classifier: Operating System :: MacOS :: MacOS X
Classifier: Operating System :: Microsoft :: Windows
License-File: LICENSE
Requires-Dist: requests
Requires-Dist: tabulate
